llm_editcode.py
llm_editcode-0.2.dist-info/METADATA
llm_editcode-0.2.dist-info/WHEEL
llm_editcode-0.2.dist-info/entry_points.txt
llm_editcode-0.2.dist-info/licenses/LICENSE
llm_editcode-0.2.dist-info/RECORD
